{
	"animations": [
		{
			"loop": false,
			"offsets": [
				0,
				0
			],
			"anim": "idle",
			"fps": 24,
			"name": "sayori idle",
			"indices": []
		},
		{
			"loop": true,
			"offsets": [
				0,
				0
			],
			"anim": "idle-loop",
			"fps": 24,
			"name": "sayori idle",
			"indices": [
				6,
				7
			]
		},
		{
			"loop": false,
			"offsets": [
				10,
				20
			],
			"anim": "singLEFT",
			"fps": 24,
			"name": "sayori left",
			"indices": []
		},
		{
			"loop": true,
			"offsets": [
				10,
				20
			],
			"anim": "singLEFT-loop",
			"fps": 24,
			"name": "sayori left",
			"indices": [
				6,
				7
			]
		},
		{
			"loop": false,
			"offsets": [
				11,
				20
			],
			"anim": "singDOWN",
			"fps": 24,
			"name": "sayori down",
			"indices": []
		},
		{
			"loop": true,
			"offsets": [
				11,
				20
			],
			"anim": "singDOWN-loop",
			"fps": 24,
			"name": "sayori down",
			"indices": [
				6,
				7
			]
		},
		{
			"loop": false,
			"offsets": [
				7,
				6
			],
			"anim": "singUP",
			"fps": 24,
			"name": "sayori up",
			"indices": []
		},
		{
			"loop": true,
			"offsets": [
				7,
				6
			],
			"anim": "singUP-loop",
			"fps": 24,
			"name": "sayori up",
			"indices": [
				6,
				7
			]
		},
		{
			"loop": false,
			"offsets": [
				-40,
				-10
			],
			"anim": "singRIGHT",
			"fps": 24,
			"name": "sayori right",
			"indices": []
		},
		{
			"loop": true,
			"offsets": [
				-40,
				-10
			],
			"anim": "singRIGHT-loop",
			"fps": 24,
			"name": "sayori right",
			"indices": [
				6,
				7
			]
		}
	],
	"no_antialiasing": false,
	"image": "characters/bonus/sayorbee",
	"position": [
		0,
		-180
	],
	"healthicon": "bee-sayori",
	"flip_x": false,
	"healthbar_colors": [
		87,
		187,
		230
	],
	"camera_position": [
		0,
		140
	],
	"sing_duration": 6.1,
	"scale": 0.9
}